{
  "identity": {
    "chip_name": "Generic Clause 22 PHY",
    "phy_id": "0x00000000",
    "phy_id_mask": "0x00000000"
  },
  "cmd_templates": {
    "std_c22": {
      "format": "mdio {bus} phy {phy_addr} raw {reg} {data}/{mask}",
      "desc": "Standard Clause 22 Write"
    },
    "std_c22_read": {
      "format": "mdio {bus} phy {phy_addr} raw {reg}",
      "desc": "Standard Clause 22 Read"
    }
  },
  "test_modes": {
    "General_Ops": {
      "options": [
        {
          "name": "Soft Reset",
          "sequence": [
            { "action": "WRITE", "reg": "0", "val": "1", "shift": 15, "mask": "0x7FFF", "comment": "Bit 15 Reset" }
          ]
        },
        {
          "name": "Read ID",
          "sequence": [
            { "action": "READ", "template": "std_c22_read", "reg": "2", "comment": "Read PHY ID 1" },
            { "action": "READ", "template": "std_c22_read", "reg": "3", "comment": "Read PHY ID 2" }
          ]
        }
      ]
    }
  }
}